lsmrestapiutilities/__init__.py
lsmrestapiutilities/api.py
lsmrestapiutilities/consts.py
lsmrestapiutilities/tests.py
lsmrestapiutilities-1.4.2.dist-info/LICENSE
lsmrestapiutilities-1.4.2.dist-info/METADATA
lsmrestapiutilities-1.4.2.dist-info/WHEEL
lsmrestapiutilities-1.4.2.dist-info/top_level.txt
lsmrestapiutilities-1.4.2.dist-info/RECORD
