Metadata-Version: 2.1
Name: lsmrestapiutilities
Version: 1.4.2
Summary: UNKNOWN
Home-page: https://github.com/bugg86/LSM-REST-API-Utilities
Author: Jack Fink
Author-email: jackfink68@yahoo.com
License: MIT
Keywords: lsm rest api utilities
Platform: UNKNOWN
License-File: LICENSE
Requires-Dist: requests
Requires-Dist: riotapiutilities
